pylibseekdb_runtime/__init__.py
pylibseekdb_runtime/libseekdb_python.so.0.gz
seekdb_lib/dummy.cpython-312-x86_64-linux-gnu.so
pylibseekdb_runtime-0.0.1.dev8.dist-info/METADATA
pylibseekdb_runtime-0.0.1.dev8.dist-info/WHEEL
pylibseekdb_runtime-0.0.1.dev8.dist-info/top_level.txt
pylibseekdb_runtime-0.0.1.dev8.dist-info/RECORD
