Metadata-Version: 2.1
Name: pylibseekdb_runtime
Version: 0.0.1.dev8
Summary: OceanBase SeekDB
Home-page: https://github.com/oceanbase/seekdb
Author: OceanBase
Author-email: open_oceanbase@oceanbase.com
Maintainer: OceanBase
Maintainer-email: open_oceanbase@oceanbase.com
License: Apache 2.0
Project-URL: Homepage, https://github.com/oceanbase/seekdb
Project-URL: Repository, https://github.com/oceanbase/seekdb
Project-URL: Documentation, https://github.com/oceanbase/seekdb
Project-URL: Bug Tracker, https://github.com/oceanbase/seekdb/issues
Keywords: database,oceanbase,embed,sql,AI
Classifier: Development Status :: 4 - Beta
Classifier: Intended Audience :: Developers
Classifier: Operating System :: POSIX :: Linux
Classifier: Programming Language :: Python :: 3
Classifier: Programming Language :: Python :: 3.8
Classifier: Programming Language :: Python :: 3.9
Classifier: Programming Language :: Python :: 3.10
Classifier: Programming Language :: Python :: 3.11
Classifier: Programming Language :: Python :: 3.12
Classifier: Programming Language :: Python :: 3.13
Classifier: Programming Language :: Python :: 3.14
Classifier: Programming Language :: C++
Classifier: Topic :: Database
Classifier: Topic :: Software Development :: Libraries :: Python Modules
Requires-Python: >=3.8
